pynamicalsys/__init__.py
pynamicalsys/__version__.py
pynamicalsys/common/__init__.py
pynamicalsys/common/basin_analysis.py
pynamicalsys/common/recurrence_quantification_analysis.py
pynamicalsys/common/time_series_metrics.py
pynamicalsys/common/utils.py
pynamicalsys/continuous_time/__init__.py
pynamicalsys/continuous_time/chaotic_indicators.py
pynamicalsys/continuous_time/models.py
pynamicalsys/continuous_time/numerical_integrators.py
pynamicalsys/continuous_time/trajectory_analysis.py
pynamicalsys/continuous_time/validators.py
pynamicalsys/core/__init__.py
pynamicalsys/core/basin_metrics.py
pynamicalsys/core/continuous_dynamical_systems.py
pynamicalsys/core/discrete_dynamical_systems.py
pynamicalsys/core/hamiltonian_systems.py
pynamicalsys/core/plot_styler.py
pynamicalsys/core/time_series_metrics.py
pynamicalsys/discrete_time/__init__.py
pynamicalsys/discrete_time/dynamical_indicators.py
pynamicalsys/discrete_time/models.py
pynamicalsys/discrete_time/trajectory_analysis.py
pynamicalsys/discrete_time/transport.py
pynamicalsys/discrete_time/validators.py
pynamicalsys/hamiltonian_systems/__init__.py
pynamicalsys/hamiltonian_systems/chaotic_indicators.py
pynamicalsys/hamiltonian_systems/models.py
pynamicalsys/hamiltonian_systems/numerical_integrators.py
pynamicalsys/hamiltonian_systems/trajectory_analysis.py
pynamicalsys/hamiltonian_systems/validators.py
pynamicalsys-1.4.9.dist-info/licenses/LICENSE
pynamicalsys-1.4.9.dist-info/METADATA
pynamicalsys-1.4.9.dist-info/WHEEL
pynamicalsys-1.4.9.dist-info/top_level.txt
pynamicalsys-1.4.9.dist-info/RECORD
