Metadata-Version: 2.4
Name: pynamicalsys
Version: 1.4.9
Summary: A Python toolkit for the analysis of dynamical systems
Author-email: Matheus Rolim Sales <rolim.sales.m@gmail.com>
License-Expression: GPL-3.0-only
Classifier: Programming Language :: Python :: 3
Classifier: Operating System :: OS Independent
Classifier: Intended Audience :: Science/Research
Classifier: Topic :: Scientific/Engineering :: Physics
Classifier: Topic :: Software Development :: Libraries :: Python Modules
Requires-Python: <3.14,>=3.8
License-File: LICENSE
Requires-Dist: numpy>=1.21
Requires-Dist: matplotlib>=3.4
Requires-Dist: numba>=0.55
Requires-Dist: scipy>=0.6
Requires-Dist: scikit-learn>=0.14
Requires-Dist: ipython<9,>=8.0
Dynamic: license-file
